soil/.VERSION.~undo-tree~
soil/.analysis.py.~undo-tree~
soil/.environment.py.~undo-tree~
soil/.stats.py.~undo-tree~
soil/VERSION
soil/__init__.py
soil/__main__.py
soil/analysis.py
soil/config.py
soil/datacollection.py
soil/debugging.py
soil/environment.py
soil/events.py
soil/exporters.py
soil/history.py
soil/network.py
soil/serialization.py
soil/settings.py
soil/simulation.py
soil/stats.py
soil/time.py
soil/utils.py
soil/version.py
soil/visualization.py
soil/agents/.__init__.py.~undo-tree~
soil/agents/BassModel.py
soil/agents/BigMarketModel.py
soil/agents/CounterModel.py
soil/agents/DrawingAgent.py
soil/agents/Geo.py
soil/agents/IndependentCascadeModel.py
soil/agents/ModelM2.py
soil/agents/SISaModel.py
soil/agents/SentimentCorrelationModel.py
soil/agents/__init__.py
soil/agents/evented.py
soil/agents/fsm.py
soil/agents/network_agents.py
soil/web/.gitignore
soil/web/README.md
soil/web/__init__.py
soil/web/__main__.py
soil/web/config.yml
soil/web/run.py
soil/web/static/css/main.css
soil/web/static/css/timeline.css
soil/web/static/img/logo_gsi.svg
soil/web/static/img/logo_soil.png
soil/web/static/img/background/map.png
soil/web/static/img/background/map_4800x2860.jpg
soil/web/static/img/svg/home.svg
soil/web/static/img/svg/person.svg
soil/web/static/img/svg/plus.svg
soil/web/static/img/svg/target.svg
soil/web/static/img/svg/time.svg
soil/web/static/js/socket.js
soil/web/static/js/template.js
soil/web/static/js/timeline.js
soil/web/static/js/visualization.js
soil/web/templates/index.html
soil-0.20.8.dist-info/LICENSE
soil-0.20.8.dist-info/METADATA
soil-0.20.8.dist-info/WHEEL
soil-0.20.8.dist-info/entry_points.txt
soil-0.20.8.dist-info/top_level.txt
soil-0.20.8.dist-info/RECORD
