Metadata-Version: 2.1
Name: soil
Version: 0.20.8
Summary: An Agent-Based Social Simulator for Social Networks
Home-page: https://github.com/gsi-upm/soil
Author: J. Fernando Sanchez
Author-email: jf.sanchez@upm.es
License: UNKNOWN
Download-URL: https://github.com/gsi-upm/soil/archive/0.20.8.tar.gz
Keywords: agent,social,simulator
Platform: UNKNOWN
Classifier: Development Status :: 5 - Production/Stable
Classifier: Environment :: Console
Classifier: Intended Audience :: End Users/Desktop
Classifier: Intended Audience :: Developers
Classifier: License :: OSI Approved :: Apache Software License
Classifier: Operating System :: MacOS :: MacOS X
Classifier: Operating System :: Microsoft :: Windows
Classifier: Operating System :: POSIX
Classifier: Programming Language :: Python :: 3
Requires-Dist: Jinja2
Requires-Dist: Mesa (>=0.8)
Requires-Dist: SALib (>=1.3)
Requires-Dist: matplotlib
Requires-Dist: networkx (>=2.5)
Requires-Dist: numpy
Requires-Dist: pandas (>=0.23)
Requires-Dist: pyyaml (>=5.1)
Requires-Dist: tsih (>=0.1.9)
Provides-Extra: all
Requires-Dist: mesa (>=0.8.9) ; extra == 'all'
Requires-Dist: scipy (>=1.3) ; extra == 'all'
Requires-Dist: tornado ; extra == 'all'
Provides-Extra: geo
Requires-Dist: scipy (>=1.3) ; extra == 'geo'
Provides-Extra: mesa
Requires-Dist: mesa (>=0.8.9) ; extra == 'mesa'
Provides-Extra: web
Requires-Dist: tornado ; extra == 'web'
